{"index.md":"D8XyVC8D","master_advanced_chatter_actions_activity.md":"DxFe2BV6","master_advanced_chatter_actions_file.md":"BISsxoUh","master_advanced_chatter_actions_follower.md":"DbFjhc4z","master_advanced_chatter_actions_log-note.md":"BmgIfMaz","master_advanced_chatter_actions_message.md":"uhZJoeXo","master_advanced_chatter_introduction.md":"BZwolFvW","master_contact_configurations.md":"DKozGO92","master_contact_contacts.md":"8zB6ba0m","master_employees_configurations.md":"DucnE5B1","master_employees_departments.md":"DyJrDE7J","master_employees_employees.md":"9YW0z6eh","master_introduction.md":"7f_HMdbt","master_inventories_configurations_delivery.md":"BEWsGEXl","master_inventories_configurations_products.md":"B0MsCEH3","master_inventories_configurations_warehouse-management.md":"huq1d0mg","master_inventories_operations_adjustments.md":"Dr7GkvJc","master_inventories_operations_transfers.md":"DPshCKjH","master_inventories_products_lots-serial-number.md":"B2nCu8A0","master_inventories_products_packages.md":"sOIJb4zM","master_inventories_products_products.md":"BMqTUOni","master_inventories_settings.md":"BgigxhOW","master_invoice_configurations.md":"DDnRH9Vq","master_invoice_customers_credit-notes.md":"OATWPXTm","master_invoice_customers_customers.md":"BD8i6Rf9","master_invoice_customers_invoices.md":"HM0lxAAR","master_invoice_customers_payments.md":"7_SNiFeR","master_invoice_customers_products.md":"DlTInYA5","master_invoice_introduction.md":"CB3R1wkr","master_invoice_settings.md":"B94r9yYi","master_invoice_vendors_bills.md":"DR8MTRzB","master_invoice_vendors_payments.md":"CReMd2FD","master_invoice_vendors_products.md":"DGtqtvda","master_invoice_vendors_refunds.md":"C-kZDH6Q","master_invoice_vendors_vendors.md":"BmIFbE23","master_project_configurations.md":"me2lgaUf","master_project_projects.md":"gbjUNwPw","master_project_settings.md":"BGK0bBz_","master_project_tasks.md":"fjnakfu5","master_purchase_configurations.md":"Bw90pUxj","master_purchase_orders_purchase-agreements.md":"x15aniRr","master_purchase_orders_purchase-orders.md":"CiWmGrP1","master_purchase_orders_quotations.md":"C2asVYf6","master_purchase_orders_vendors.md":"DkalPZlK","master_purchase_products.md":"BMhpMUgA","master_purchase_settings.md":"BTd7Ytsy","master_recruitment_applications.md":"D_UWD1qF","master_recruitment_configuration.md":"DRSKhGRe","master_sales_configurations.md":"DH6vFATn","master_sales_orders_customers.md":"DK1V94VN","master_sales_orders_orders.md":"B-AtMjHT","master_sales_orders_quotations.md":"C7HjVQOF","master_sales_products.md":"iKxkCvXc","master_sales_settings.md":"BWjbOa00","master_sales_toinvoice.md":"Ru18pLe_","master_timeoff_configuration.md":"CrmOZewC","master_timeoff_management.md":"BpgTmkhz","master_timeoff_my-time.md":"BG71OfQq","master_timeoff_overview.md":"B9fv6IOv","master_timeoff_reporting.md":"BjLrL8WP","master_website_blog-posts.md":"CWmHGd0N","master_website_configurations.md":"DhKqlSp-","master_website_customers.md":"D6ujSPuM","master_website_pages.md":"CGSRy6Lu","master_website_settings.md":"uvb9z3MG"}
